pytesseraxcocr/__init__.py
pytesseraxcocr/image_ocr.py
pytesseraxcocr-0.3.9.dist-info/METADATA
pytesseraxcocr-0.3.9.dist-info/WHEEL
pytesseraxcocr-0.3.9.dist-info/top_level.txt
pytesseraxcocr-0.3.9.dist-info/RECORD
