Metadata-Version: 2.1
Name: pytesseraxcocr
Version: 0.3.9
License: MIT
Requires-Dist: requests
Requires-Dist: pyzbar
Requires-Dist: Pillow
